farm_ng/amiga/__init__.py
farm_ng/amiga/amiga.proto
farm_ng/amiga/amiga_pb2.py
farm_ng/amiga/amiga_pb2.pyi
farm_ng/amiga/amiga_pb2_grpc.py
farm_ng/canbus/__init__.py
farm_ng/canbus/amiga_v6.proto
farm_ng/canbus/amiga_v6_pb2.py
farm_ng/canbus/amiga_v6_pb2.pyi
farm_ng/canbus/amiga_v6_pb2_grpc.py
farm_ng/canbus/canbus.proto
farm_ng/canbus/canbus_pb2.py
farm_ng/canbus/canbus_pb2.pyi
farm_ng/canbus/canbus_pb2_grpc.py
farm_ng/canbus/packet.py
farm_ng/canbus/tool_control.proto
farm_ng/canbus/tool_control_pb2.py
farm_ng/canbus/tool_control_pb2.pyi
farm_ng/canbus/tool_control_pb2_grpc.py
farm_ng/filter/__init__.py
farm_ng/filter/filter.proto
farm_ng/filter/filter_pb2.py
farm_ng/filter/filter_pb2.pyi
farm_ng/filter/filter_pb2_grpc.py
farm_ng/gps/__init__.py
farm_ng/gps/gps.proto
farm_ng/gps/gps_pb2.py
farm_ng/gps/gps_pb2.pyi
farm_ng/gps/gps_pb2_grpc.py
farm_ng/imu/__init__.py
farm_ng/imu/imu_pb2.py
farm_ng/imu/imu_pb2.pyi
farm_ng/imu/imu_pb2_grpc.py
farm_ng/oak/__init__.py
farm_ng/oak/oak.proto
farm_ng/oak/oak_pb2.py
farm_ng/oak/oak_pb2.pyi
farm_ng/oak/oak_pb2_grpc.py
farm_ng/track/__init__.py
farm_ng/track/track.proto
farm_ng/track/track_pb2.py
farm_ng/track/track_pb2.pyi
farm_ng/track/track_pb2_grpc.py
farm_ng/track/utils.py
farm_ng_amiga-2.3.4.dist-info/LICENSE
farm_ng_amiga-2.3.4.dist-info/METADATA
farm_ng_amiga-2.3.4.dist-info/WHEEL
farm_ng_amiga-2.3.4.dist-info/top_level.txt
farm_ng_amiga-2.3.4.dist-info/RECORD
