Metadata-Version: 2.1
Name: farm_ng_amiga
Version: 2.3.4
Summary: Amiga development kit for third party hardware or software extensions
Home-page: https://github.com/farm-ng/farm-ng-amiga
Download-URL: https://github.com/farm-ng/farm-ng-amiga
Author: farm-ng Inc.
Author-email: info@farm-ng.com
Keywords: robotics
Classifier: Development Status :: 4 - Beta
Classifier: Intended Audience :: Developers
Classifier: License :: Other/Proprietary License
Classifier: Operating System :: OS Independent
Classifier: Programming Language :: Python :: 3
Classifier: Topic :: Software Development
Classifier: Framework :: Robot Framework
Requires-Python: >=3.6
License-File: LICENSE
Requires-Dist: grpcio
Requires-Dist: protobuf<=5.27.5
Requires-Dist: farm-ng-core
Provides-Extra: dev
Requires-Dist: pytest; extra == "dev"
Requires-Dist: pytest-asyncio; extra == "dev"
Requires-Dist: pytest-mypy; extra == "dev"
Requires-Dist: pylint-protobuf; extra == "dev"
Requires-Dist: pre-commit; extra == "dev"
Requires-Dist: mypy; extra == "dev"
Requires-Dist: types-protobuf; extra == "dev"
Requires-Dist: pylint; extra == "dev"
Requires-Dist: grpcio-tools; extra == "dev"
Requires-Dist: mypy-protobuf; extra == "dev"
